setup.py
src/gitgud/__init__.py
src/gitgud/gitgud.py
src/gitgud.egg-info/PKG-INFO
src/gitgud.egg-info/SOURCES.txt
src/gitgud.egg-info/dependency_links.txt
src/gitgud.egg-info/entry_points.txt
src/gitgud.egg-info/requires.txt
src/gitgud.egg-info/top_level.txt