Metadata-Version: 1.0
Name: gitgud
Version: 1.1
Summary: Git Gud - a utility for when you are told to 'get good'
Home-page: https://github.com/fsufitch/git-gud
Author: Filip Sufitchi
Author-email: fsufitchi@gmail.com
License: UNKNOWN
Platform: UNKNOWN
